Workbook
Name XRefCopy52Row: #REF!
Name BExZNH3VISFF4NQI11BZDP5IQ7VG: #REF!
Name BExQDGQCN7ZW41QDUHOBJUGQAX40: #REF!
Name XRefCopy74: #REF!
Name BEx9IT5QNZWKM6YQ5WER0DC2PMMU: #REF!
Name BExZM7JVLG0W8EG5RBU915U3SKBY: #REF!
Name BEx9175B70QXYAU5A8DJPGZQ46L9: #REF!
Name XRefPaste29Row: #REF!
Name BExO5A8PZD9EUHC5CMPU6N3SQ15L: #REF!
Name BExKU82I99FEUIZLODXJDOJC96CQ: #REF!
Name BExQIBWPAXU7HJZLKGJZY3EB7MIS: #REF!
Name BExD71LTOE015TV5RSAHM8NT8GVW: #REF!
Name BExTUA5F7V4LUIIAM17J3A8XF3JE: #REF!
Name BExKSJTWG9L3FCX8FLK4EMUJMF27: #REF!
Name BEx91L8FLL5CWLA2CDHKCOMGVDZN: #REF!
Name BExVYQIXPEM6J4JVP78BRHIC05PV: #REF!
Name BExB6C8X6JYRLKZKK17VE3QUNL3D: #REF!
Name BExQ9E6FBAXTHGF3RXANFIA77GXP: #REF!
Name BExKO06X0EAD3ABEG1E8PWLDWHBA: #REF!
Name XRefPaste99Row: #REF!
Name XRefCopy68: #REF!
Name XRefPaste7: #REF!
Name BEx1UESH4KDWHYESQU2IE55RS3LI: #REF!
Name BExU147D6RPG6ZVTSXRKFSVRHSBG: #REF!
Name BExCXQUFBMXQ1650735H48B1AZT3: #REF!
Name XREF_COLUMN_25: #REF!
Name XRefPaste17: #REF!
Name XRefPaste70: #REF!
Name BExZTW6ECBRA0BBITWBQ8R93RMCL: #REF!
Name BExGNZO44DEG8CGIDYSEGDUQ531R: #REF!
Name BExGVV6OOLDQ3TXZK51TTF3YX0WN: #REF!
Name BExF19CT3MMZZ2T5EWMDNG3UOJ01: #REF!
Name XRefPaste124: #REF!
Name BExERRUIKIOATPZ9U4HQ0V52RJAU: #REF!
Name BExB74PS5P9G0P09Y6DZSCX0FLTJ: #REF!
Name BExU7O2BJ6D5YCKEL6FD2EFCWYRX: #REF!
Name BExD2DMHH1HWXQ9W0YYMDP8AAX8Q: #REF!
Name BExOJ3AKZ9BCBZT3KD8WMSLK6MN2: #REF!
Name XRefCopy146: #REF!
Name BEx3Q0VWPU5EQECK7MQ47TYJ3SWW: #REF!
Name BEx9FJTSRCZ3ZXT3QVBJT5NF8T7V: #REF!
Name XRefCopy33Row: #REF!
Name BExKH3FV5U5O6XZM7STS3NZKQFGJ: #REF!
Name BExU76ZHCJM8I7VSICCMSTC33O6U: #REF!
Name BExS1BNVGNSGD4EP90QL8WXYWZ66: #REF!
Name BExAYR2JZCJBUH6F1LZC2A7JIVRJ: #REF!
Name XRefCopy74: #REF!
Name XRefPaste5Row: #REF!
Name BExQFPNFKA36IAPS22LAUMBDI4KE: #REF!
Name BExSAY9CA9TFXQ9M9FBJRGJO9T9E: #REF!
Name BExKQJGAAWNM3NT19E9I0CQDBTU0: #REF!
Name BExGYCNATXZY2FID93B17YWIPPRD: #REF!
Name BExF7K88K7ASGV6RAOAGH52G04VR: #REF!
Name XRefCopy135: #REF!
Name BExB1WI6M8I0EEP1ANUQZCFY24EV: #REF!
Name BExES44RHHDL3V7FLV6M20834WF1: #REF!
Name BExQAELFYH92K8CJL155181UDORO: #REF!
Name BExAYY9H9COOT46HJLPVDLTO12UL: #REF!
Name BExGWLEOC70Z8QAJTPT2PDHTNM4L: #REF!
Name BExKLLKVVHT06LA55JB2FC871DC5: #REF!

Sheet DRE
G9: JAN | H9: FEV | I9: MAR | J9: ABR | K9: MAI | L9: JUN | M9: JUL | N9: AGO | O9: SET | P9: OUT | Q9: Nov | R9: Dez | S9: Total
S10: Realizado
B12: ( = ) | C12: Receita de Vendas | G12: =FC!G16 -> 987500 | H12: =FC!H16 -> 1027000 | I12: =FC!I16 -> 1066500 | J12: =FC!J16 -> 1106000 | K12: =FC!K16 -> 1145500 | L12: =FC!L16 -> 1185000 | M12: =FC!M16 -> 1224500 | N12: =FC!N16 -> 1264000 | ... R12: =FC!R16 -> 1422000 | S12: =SUM(G12:R12)/12 -> 1204750
B13: ( - ) | C13: Despesas de Comissão | G13: =G12*5% -> 49375 | H13: =H12*5% -> 51350 | I13: =I12*5% -> 53325 | J13: =J12*5% -> 55300 | K13: =K12*5% -> 57275 | L13: =L12*5% -> 59250 | M13: =M12*5% -> 61225 | N13: =N12*5% -> 63200 | ... R13: =R12*5% -> 71100
B14: ( - ) | C14: Despesas de Impostos (PIS/COFINS/ISS) | G14: =G12*8.5% -> 83937.5 | H14: =H12*8.5% -> 87295 | I14: =I12*8.5% -> 90652.5 | J14: =J12*8.5% -> 94010 | K14: =K12*8.5% -> 97367.5 | L14: =L12*8.5% -> 100725 | M14: =M12*8.5% -> 104082.5 | N14: =N12*8.5% -> 107440 | ... R14: =R12*8.5% -> 120870 | S14: 111350
B15: ( = ) | C15: Receita Líquida | G15: =G12-G13-G14 -> 854187.5 | H15: =H12-H13-H14 -> 888355 | I15: =I12-I13-I14 -> 922522.5 | J15: =J12-J13-J14 -> 956690 | K15: =K12-K13-K14 -> 990857.5 | L15: =L12-L13-L14 -> 1025025 | M15: =M12-M13-M14 -> 1059192.5 | N15: =N12-N13-N14 -> 1093360 | ... S15: =S12-S13-S14 -> 1093400
C17: Custos
B18: ( - ) | C18: Despesas LOGISTICA | G18: =G12*11% -> 108625 | H18: =H12*11% -> 112970 | I18: =I12*11% -> 117315 | J18: =J12*11% -> 121660 | K18: =K12*11% -> 126005 | L18: =L12*11% -> 130350 | M18: =M12*11% -> 134695 | N18: =N12*11% -> 139040 | ... R18: =R12*11% -> 156420 | S18: =SUM(G18:R18)/12 -> 132522.5
B19: ( - ) | C19: Outros Custos Diretos (Insumos/materiais) | G19: =FC!G27 -> 180000 | H19: =FC!H27 -> 180000 | I19: =FC!I27 -> 190000 | J19: =FC!J27 -> 190000 | K19: =FC!K27 -> 200000 | L19: =FC!L27 -> 210000 | M19: =FC!M27 -> 210000 | N19: =FC!N27 -> 220000 | ... R19: =FC!R27 -> 230000 | S19: =SUM(G19:R19)/12 -> 207500
B20: ( - ) | C20: Despesas Equipamentos / Infraestrutura | G20: =FC!G32 -> 34000 | H20: =FC!H32 -> 34000 | I20: =FC!I32 -> 34000 | J20: =FC!J32 -> 34000 | K20: =FC!K32 -> 34000 | L20: =FC!L32 -> 34000 | M20: =FC!M32 -> 34000 | N20: =FC!N32 -> 40000 | ... R20: =FC!R32 -> 40000 | S20: =SUM(G20:R20)/12 -> 36500
B21: ( - ) | C21: Provisão Manutenção Maq. Etc | G21: =FC!G33 -> 5000 | H21: =FC!H33 -> 5000 | I21: 5000 | J21: =FC!J33 -> 5000 | K21: =FC!K33 -> 5000 | L21: =FC!L33 -> 5000 | M21: =FC!M33 -> 5000 | N21: =FC!N33 -> 5000 | O21: =FC!O33 -> 5000 | P21: =FC!P33 -> 5000 | Q21: =FC!Q33 -> 5000 | R21: =FC!R33 -> 5000 | S21: =SUM(G21:R21)/12 -> 5000
B22: ( = ) | C22: Lucro Bruto | G22: =SUM(G18:G21) -> 327625 | H22: =SUM(H18:H21) -> 331970 | I22: =SUM(I18:I21) -> 346315 | J22: =SUM(J18:J21) -> 350660 | K22: =SUM(K18:K21) -> 365005 | L22: =SUM(L18:L21) -> 379350 | M22: =SUM(M18:M21) -> 383695 | N22: =SUM(N18:N21) -> 404040 | ... R22: =SUM(R18:R21) -> 431420 | S22: =S15-S18-S19-S20 -> 716877.5
C24: Despesas
B25: ( - ) | C25: Despesas de Pessoal | G25: =FC!G18 -> 145000 | H25: =FC!H18 -> 160000 | I25: =FC!I18 -> 160000 | J25: =FC!J18 -> 180000 | K25: =FC!K18 -> 180000 | L25: =FC!L18 -> 180000 | M25: =FC!M18 -> 200000 | N25: =FC!N18 -> 200000 | ... R25: =FC!R18 -> 200000 | S25: 70000
B26: ( - ) | C26: Despesas de Benefícios | G26: =G25*20% -> 29000 | H26: =H25*20% -> 32000 | I26: =I25*20% -> 32000 | J26: =J25*20% -> 36000 | K26: =K25*20% -> 36000 | L26: =L25*20% -> 36000 | M26: =M25*20% -> 40000 | N26: =N25*20% -> 40000 | ... R26: =R25*20% -> 40000
B27: ( - ) | C27: Despesas de Impostos (INSS/FGTS) | G27: =G25*45% -> 65250 | H27: =H25*45% -> 72000 | I27: =I25*45% -> 72000 | J27: =J25*45% -> 81000 | K27: =K25*45% -> 81000 | L27: =L25*45% -> 81000 | M27: =M25*45% -> 90000 | N27: =N25*45% -> 90000 | ... R27: =R25*45% -> 90000 | S27: =SUM(G27:R27)/12 -> 82687.5
B28: ( - ) | C28: Despesas de Pró-Labore | G28: =FC!G22 -> 120000 | H28: =FC!H22 -> 120000 | I28: =FC!I22 -> 130000 | J28: =FC!J22 -> 140000 | K28: =FC!K22 -> 150000 | L28: =FC!L22 -> 160000 | M28: =FC!M22 -> 160000 | N28: =FC!N22 -> 160000 | ... R28: =FC!R22 -> 200000 | S28: =SUM(G28:R28)/12 -> 158333.33
B29: ( - ) | C29: Provisão de Férias/13o./Rescisões | G29: =FC!G23 -> 29000 | H29: =FC!H23 -> 32000 | I29: =FC!I23 -> 32000 | J29: =FC!J23 -> 36000 | K29: =FC!K23 -> 36000 | L29: =FC!L23 -> 36000 | M29: =FC!M23 -> 40000 | N29: =FC!N23 -> 40000 | ... R29: =FC!R23 -> 40000 | S29: =SUM(G29:R29)/12 -> 36750
B30: ( - ) | C30: Despesas de Aluguel (Luz / Água) | G30: =FC!G24 -> 32000 | H30: =FC!H24 -> 32000 | I30: =FC!I24 -> 32000 | J30: =FC!J24 -> 32000 | K30: =FC!K24 -> 32000 | L30: =FC!L24 -> 32000 | M30: =FC!M24 -> 32000 | N30: =FC!N24 -> 32000 | ... R30: =FC!R24 -> 32000 | S30: =SUM(G30:R30)/12 -> 32000
B31: ( - ) | C31: Despesas de MKT | G31: =FC!G25 -> 4500 | H31: =FC!H25 -> 4500 | I31: =FC!I25 -> 4500 | J31: =FC!J25 -> 4500 | K31: =FC!K25 -> 4500 | L31: =FC!L25 -> 4500 | M31: =FC!M25 -> 6500 | N31: =FC!N25 -> 6500 | ... R31: =FC!R25 -> 6500 | S31: =SUM(G31:R31)/12 -> 5500
B32: ( - ) | C32: Despesas de TI | G32: =FC!G26 -> 20000 | H32: =FC!H26 -> 20000 | I32: =FC!I26 -> 20000 | J32: =FC!J26 -> 20000 | K32: =FC!K26 -> 20000 | L32: =FC!L26 -> 20000 | M32: =FC!M26 -> 22000 | N32: =FC!N26 -> 22000 | ... R32: =FC!R26 -> 22000 | S32: =SUM(G32:R32)/12 -> 21000
B33: ( - ) | C33: Despesas DIVERSAS | G33: =FC!G28 -> 30000 | H33: =FC!H28 -> 30000 | I33: =FC!I28 -> 30000 | J33: =FC!J28 -> 30000 | K33: =FC!K28 -> 33000 | L33: =FC!L28 -> 33000 | M33: =FC!M28 -> 33000 | N33: =FC!N28 -> 33000 | ... R33: =FC!R28 -> 35000 | S33: =SUM(G33:R33)/12 -> 32500
B34: ( - ) | C34: Despesas Manut. PREDIAL | G34: =FC!G29 -> 6000 | H34: =FC!H29 -> 6000 | I34: =FC!I29 -> 6000 | J34: =FC!J29 -> 6000 | K34: =FC!K29 -> 6000 | L34: =FC!L29 -> 6000 | M34: =FC!M29 -> 6000 | N34: =FC!N29 -> 6000 | ... R34: =FC!R29 -> 6000 | S34: =SUM(G34:R34)/12 -> 6000
B35: ( - ) | C35: Despesas Exames Outros Laboratórios | G35: =FC!G31 -> 18000 | H35: =FC!H31 -> 18000 | I35: =FC!I31 -> 18000 | J35: =FC!J31 -> 18000 | K35: =FC!K31 -> 18000 | L35: =FC!L31 -> 18000 | M35: =FC!M31 -> 18000 | N35: =FC!N31 -> 20000 | ... R35: =FC!R31 -> 20000 | S35: =SUM(G35:R35)/12 -> 18833.333
B36: ( - ) | C36: Desp. Financeiras / Empréstimos | G36: =FC!G35 -> 20000 | H36: =FC!H35 -> 20000 | I36: =FC!I35 -> 20000 | J36: =FC!J35 -> 20000 | K36: =FC!K35 -> 20000 | L36: =FC!L35 -> 20000 | M36: =FC!M35 -> 20000 | N36: =FC!N35 -> 20000 | ... R36: =FC!R35 -> 20000 | S36: =SUM(G36:R36)/12 -> 20000
B37: ( = ) | C37: Total das Saídas | G37: =SUM(G25:G36) -> 518750 | H37: =SUM(H25:H36) -> 546500 | I37: =SUM(I25:I36) -> 556500 | J37: =SUM(J25:J36) -> 603500 | K37: =SUM(K25:K36) -> 616500 | L37: =SUM(L25:L36) -> 626500 | M37: =SUM(M25:M36) -> 667500 | N37: =SUM(N25:N36) -> 669500 | ... R37: =SUM(R25:R36) -> 711500 | S37: =SUM(S14:S36) -> 2786754.2
B39: ( - ) | C39: Despesas de Impostos (PIS/COFINS)
B41: ( = ) | C41: Resultado Líquido | G41: =G15-G22-G37-G39 -> 7812.5 | H41: =H15-H22-H37-H39 -> 9885 | I41: =I15-I22-I37-I39 -> 19707.5 | J41: =J15-J22-J37-J39 -> 2530 | K41: =K15-K22-K37-K39 -> 9352.5 | L41: =L15-L22-L37-L39 -> 19175 | M41: =M15-M22-M37-M39 -> 7997.5 | N41: =N15-N22-N37-N39 -> 19820 | ... R41: =R15-R22-R37-R39 -> 87110 | S41: =SUM(G41:R41) -> 317785
C42: % em relação ao Faturamento | G42: =IF(OR(G12=0,G37=0),"",G37/G12) -> 0.52531646 | H42: =IF(OR(H12=0,H37=0),"",H37/H12) -> 0.53213242 | I42: =IF(OR(I12=0,I37=0),"",I37/I12) -> 0.52180028 | J42: =IF(OR(J12=0,J37=0),"",J37/J12) -> 0.54566004 | K42: =IF(OR(K12=0,K37=0),"",K37/K12) -> 0.53819293 | L42: =IF(OR(L12=0,L37=0),"",L37/L12) -> 0.52869198 | M42: =IF(OR(M12=0,M37=0),"",M37/M12) -> 0.54512046 | N42: =IF(OR(N12=0,N37=0),"",N37/N12) -> 0.52966772 | ... R42: =IF(OR(R12=0,R37=0),"",R37/R12) -> 0.50035162
G45: =G37+G22+G14+G13 -> 979687.5 | H45: =H37+H22+H14+H13 -> 1017115 | I45: =I37+I22+I14+I13 -> 1046792.5 | J45: =J37+J22+J14+J13 -> 1103470 | K45: =K37+K22+K14+K13 -> 1136147.5 | L45: =L37+L22+L14+L13 -> 1165825 | M45: =M37+M22+M14+M13 -> 1216502.5 | N45: =N37+N22+N14+N13 -> 1244180 | ... R45: =R37+R22+R14+R13 -> 1334890
G46: 979687.5 | H46: 1017115 | I46: 1046792.5 | J46: 1103470 | K46: 1136147.5 | L46: 1165825 | M46: 1216502.5 | N46: 1244180 | O46: 1253857.5 | P46: 1315535 | Q46: 1325212.5 | R46: 1334890

Sheet FC
B7: FLUXO DE CAIXA PROJETADO -
G9: JAN | H9: FEV | I9: MAR | J9: ABR | K9: MAI | L9: JUN | M9: JUL | N9: AGO | O9: SET | P9: OUT | Q9: Nov | R9: Dez | S9: 6 | U9: 7 | W9: 8 | Y9: 9 | AA9: 10 | AC9: 11 | AE9: 12 | AF9: Total
S10: Jun | T10: Realizado | U10: Jul | V10: Realizado | W10: Ago | X10: Realizado | Y10: Set | Z10: Realizado | AA10: Out | AB10: Realizado | AC10: Nov | AD10: Realizado | AE10: Dez | AF10: Realizado
B12: Número de pedidos | G12: 12500 | H12: 13000 | I12: 13500 | J12: 14000 | K12: 14500 | L12: 15000 | M12: 15500 | N12: 16000 | O12: 16500 | P12: 17000 | Q12: 17500 | R12: 18000 | S12: =S16/S14 -> #DIV/0! | T12: 14909 | V12: 14909 | X12: 14909 | Z12: 14909 | AB12: 14909 | AD12: 14909 | AF12: =SUM(G12:R12)/12 -> 15250
B14: Ticket Médio - Em R$ | G14: 79 | H14: 79 | I14: 79 | J14: 79 | K14: 79 | L14: 79 | M14: 79 | N14: 79 | O14: 79 | P14: 79 | Q14: 79 | R14: 79 | T14: =T16/T12 -> 10.969904 | V14: =V16/V12 -> 10.969904 | X14: =X16/X12 -> 10.969904 | Z14: =Z16/Z12 -> 10.969904 | AB14: =AB16/AB12 -> 10.969904 | AD14: =AD16/AD12 -> 10.969904 | AF14: =SUM(G14:R14)/12 -> 79
B16: ( = ) | C16: Receita de Vendas | G16: =G14*G12 -> 987500 | H16: =H14*H12 -> 1027000 | I16: =I14*I12 -> 1066500 | J16: =J14*J12 -> 1106000 | K16: =K14*K12 -> 1145500 | L16: =L14*L12 -> 1185000 | M16: =M14*M12 -> 1224500 | N16: =N14*N12 -> 1264000 | ... R16: =R14*R12 -> 1422000 | S16: 1130000 | T16: 163550.3 | U16: =1391.01+108+471.66+3793.94+1247.5+1006.82+3301.45+770.92+1107.74+574.47+1782.45 -> 15555.96 | V16: 163550.3 | W16: =1391.01+108+471.66+3793.94+1247.5+1006.82+3301.45+770.92+1107.74+574.47+1782.45 -> 15555.96 | X16: 163550.3 | Y16: =1391.01+108+471.66+3793.94+1247.5+1006.82+3301.45+770.92+1107.74+574.47+1782.45 -> 15555.96 | Z16: 163550.3 | AA16: =1391.01+108+471.66+3793.94+1247.5+1006.82+3301.45+770.92+1107.74+574.47+1782.45 -> 15555.96 | AB16: 163550.3 | AC16: =1391.01+108+471.66+3793.94+1247.5+1006.82+3301.45+770.92+1107.74+574.47+1782.45 -> 15555.96 | AD16: 163550.3 | AE16: =1391.01+108+471.66+3793.94+1247.5+1006.82+3301.45+770.92+1107.74+574.47+1782.45 -> 15555.96 | AF16: =SUM(G16:R16)/12 -> 1204750
B18: ( - ) | C18: Despesas de Pessoal | G18: 145000 | H18: 160000 | I18: 160000 | J18: 180000 | K18: 180000 | L18: 180000 | M18: 200000 | N18: 200000 | O18: 200000 | P18: 200000 | Q18: 200000 | R18: 200000 | S18: 70000 | U18: 70000 | W18: 70000 | Y18: 80000 | AA18: 80000 | AC18: 80000 | AE18: 80000 | AF18: =SUM(G18:R18)/12 -> 183750 | AH18: 112280.44 | AI18: =((G18/AH18)-1)*100 -> 29.140923
B19: ( - ) | C19: Despesas de Comissão | G19: =G16*5% -> 49375 | H19: =H16*5% -> 51350 | I19: =I16*5% -> 53325 | J19: =J16*5% -> 55300 | K19: =K16*5% -> 57275 | L19: =L16*5% -> 59250 | M19: =M16*5% -> 61225 | N19: =N16*5% -> 63200 | ... R19: =R16*5% -> 71100 | AF19: =SUM(G19:R19)/12 -> 60237.5 | AH19: 27141.877 | AI19: =((G19/AH19)-1)*100 -> 81.914463
B20: ( - ) | C20: Despesas de Benefícios | G20: =G18*20% -> 29000 | H20: =H18*20% -> 32000 | I20: =I18*20% -> 32000 | J20: =J18*20% -> 36000 | K20: =K18*20% -> 36000 | L20: =L18*20% -> 36000 | M20: =M18*20% -> 40000 | N20: =N18*20% -> 40000 | ... R20: =R18*20% -> 40000 | S20: 15000 | U20: 15000 | W20: 15000 | Y20: 17000 | AA20: 17000 | AC20: 17000 | AE20: 17000 | AF20: =SUM(G20:R20)/12 -> 36750 | AH20: 14920.076 | AI20: =((G20/AH20)-1)*100 -> 94.368987
B21: ( - ) | C21: Despesas de Impostos (INSS/FGTS) | G21: =G18*45% -> 65250 | H21: =H18*45% -> 72000 | I21: =I18*45% -> 72000 | J21: =J18*45% -> 81000 | K21: =K18*45% -> 81000 | L21: =L18*45% -> 81000 | M21: =M18*45% -> 90000 | N21: =N18*45% -> 90000 | ... R21: =R18*45% -> 90000 | S21: 5000 | U21: 5000 | W21: 5000 | Y21: 5000 | AA21: 5000 | AC21: 5000 | AE21: 5000 | AF21: =SUM(G21:R21)/12 -> 82687.5 | AH21: 19892.824 | AI21: =((G21/AH21)-1)*100 -> 228.00772
B22: ( - ) | C22: Despesas de Pró-Labore | G22: 120000 | H22: 120000 | I22: 130000 | J22: 140000 | K22: 150000 | L22: 160000 | M22: 160000 | N22: 160000 | O22: 160000 | P22: 200000 | Q22: 200000 | R22: 200000 | S22: 0 | U22: 0 | W22: 0 | Y22: 0 | AA22: 0 | AC22: 0 | AE22: 0 | AF22: =SUM(G22:R22)/12 -> 158333.33 | AH22: 64000 | AI22: =((G22/AH22)-1)*100 -> 87.5
B23: ( - ) | C23: Provisão de Férias/13o./Rescisões | G23: =G18*20% -> 29000 | H23: =H18*20% -> 32000 | I23: =I18*20% -> 32000 | J23: =J18*20% -> 36000 | K23: =K18*20% -> 36000 | L23: =L18*20% -> 36000 | M23: =M18*20% -> 40000 | N23: =N18*20% -> 40000 | ... R23: =R18*20% -> 40000 | AF23: =SUM(G23:R23)/12 -> 36750 | AH23: 7480.4671 | AI23: =((G23/AH23)-1)*100 -> 287.67632
B24: ( - ) | C24: Despesas de Aluguel (Luz / Água) | G24: 32000 | H24: 32000 | I24: 32000 | J24: 32000 | K24: 32000 | L24: 32000 | M24: 32000 | N24: 32000 | O24: 32000 | P24: 32000 | Q24: 32000 | R24: 32000 | S24: 9000 | U24: 9000 | W24: 9000 | Y24: 9000 | AA24: 9000 | AC24: 9000 | AE24: 9000 | AF24: =SUM(G24:R24)/12 -> 32000 | AH24: 24963.481 | AI24: =((G24/AH24)-1)*100 -> 28.187249
B25: ( - ) | C25: Despesas de MKT | G25: 4500 | H25: 4500 | I25: 4500 | J25: 4500 | K25: 4500 | L25: 4500 | M25: 6500 | N25: 6500 | O25: 6500 | P25: 6500 | Q25: 6500 | R25: 6500 | S25: 2000 | U25: 2000 | W25: 2000 | Y25: 2000 | AA25: 2000 | AC25: 2000 | AE25: 2000 | AF25: =SUM(G25:R25)/12 -> 5500 | AH25: 2785.7143 | AI25: =((G25/AH25)-1)*100 -> 61.538462
B26: ( - ) | C26: Despesas de TI | G26: 20000 | H26: 20000 | I26: 20000 | J26: 20000 | K26: 20000 | L26: 20000 | M26: 22000 | N26: 22000 | O26: 22000 | P26: 22000 | Q26: 22000 | R26: 22000 | S26: 1500 | U26: 1500 | W26: 1500 | Y26: 1500 | AA26: 1500 | AC26: 1500 | AE26: 1500 | AF26: =SUM(G26:R26)/12 -> 21000 | AH26: 13751.296 | AI26: =((G26/AH26)-1)*100 -> 45.44084
B27: ( - ) | C27: Outros Custos Diretos (Insumos/materiais) | G27: 180000 | H27: 180000 | I27: 190000 | J27: 190000 | K27: 200000 | L27: 210000 | M27: 210000 | N27: 220000 | O27: 220000 | P27: 230000 | Q27: 230000 | R27: 230000 | S27: 30000 | U27: 30000 | W27: 30000 | Y27: 30000 | AA27: 30000 | AC27: 30000 | AE27: 30000 | AF27: =SUM(G27:R27)/12 -> 207500 | AH27: 145603.3 | AI27: =((G27/AH27)-1)*100 -> 23.623573
B28: ( - ) | C28: Despesas DIVERSAS | G28: 30000 | H28: 30000 | I28: 30000 | J28: 30000 | K28: 33000 | L28: 33000 | M28: 33000 | N28: 33000 | O28: 33000 | P28: 35000 | Q28: 35000 | R28: 35000 | S28: 7000 | U28: 7000 | W28: 7000 | Y28: 7000 | AA28: 7000 | AC28: 7000 | AE28: 7000 | AF28: =SUM(G28:R28)/12 -> 32500 | AH28: 21400.736 | AI28: =((G28/AH28)-1)*100 -> 40.182097
B29: ( - ) | C29: Despesas Manut. PREDIAL | G29: 6000 | H29: 6000 | I29: 6000 | J29: 6000 | K29: 6000 | L29: 6000 | M29: 6000 | N29: 6000 | O29: 6000 | P29: 6000 | Q29: 6000 | R29: 6000 | AF29: =SUM(G29:R29)/12 -> 6000 | AH29: 4317.04 | AI29: =((G29/AH29)-1)*100 -> 38.984119
B30: ( - ) | C30: Despesas LOGISTICA | G30: =G16*11% -> 108625 | H30: =H16*11% -> 112970 | I30: =I16*11% -> 117315 | J30: =J16*11% -> 121660 | K30: =K16*11% -> 126005 | L30: =L16*11% -> 130350 | M30: =M16*11% -> 134695 | N30: =N16*11% -> 139040 | ... R30: =R16*11% -> 156420 | S30: 22000 | U30: 22000 | W30: 22000 | Y30: 22000 | AA30: 22000 | AC30: 22000 | AE30: 22000 | AF30: =SUM(G30:R30)/12 -> 132522.5 | AH30: 76921.88 | AI30: =((G30/AH30)-1)*100 -> 41.214697
B31: ( - ) | C31: Despesas Exames Outros Laboratórios | G31: 18000 | H31: 18000 | I31: 18000 | J31: 18000 | K31: 18000 | L31: 18000 | M31: 18000 | N31: 20000 | O31: 20000 | P31: 20000 | Q31: 20000 | R31: 20000 | S31: 16000 | U31: 16000 | W31: 16000 | Y31: 16000 | AA31: 16000 | AC31: 16000 | AE31: 16000 | AF31: =SUM(G31:R31)/12 -> 18833.333 | AH31: 19478.796 | AI31: =((G31/AH31)-1)*100 -> -7.5918231
B32: ( - ) | C32: Despesas Equipamentos / Infraestrutura | G32: 34000 | H32: 34000 | I32: 34000 | J32: 34000 | K32: 34000 | L32: 34000 | M32: 34000 | N32: 40000 | O32: 40000 | P32: 40000 | Q32: 40000 | R32: 40000 | S32: 16000 | U32: 16000 | W32: 16000 | Y32: 16000 | AA32: 16000 | AC32: 16000 | AE32: 16000 | AF32: =SUM(G32:R32)/12 -> 36500 | AH32: 18227.131 | AI32: =((G32/AH32)-1)*100 -> 86.535112
B33: ( - ) | C33: Provisão Manutenção Maq. Etc | G33: 5000 | H33: 5000 | I33: 5000 | J33: 5000 | K33: 5000 | L33: 5000 | M33: 5000 | N33: 5000 | O33: 5000 | P33: 5000 | Q33: 5000 | R33: 5000 | AF33: =SUM(G33:R33)/12 -> 5000 | AH33: 5000 | AI33: =((G33/AH33)-1)*100 -> 0
B34: ( - ) | C34: Despesas de Impostos (IRPJ/CSLL/PIS/COFINS) | G34: =G16*8.5% -> 83937.5 | H34: =H16*8.5% -> 87295 | I34: =I16*8.5% -> 90652.5 | J34: =J16*8.5% -> 94010 | K34: =K16*8.5% -> 97367.5 | L34: =L16*8.5% -> 100725 | M34: =M16*8.5% -> 104082.5 | N34: =N16*8.5% -> 107440 | ... R34: =R16*8.5% -> 120870 | S34: 5000 | U34: 5000 | W34: 5000 | Y34: 5000 | AA34: 5000 | AC34: 5000 | AE34: 5000 | AF34: =SUM(G34:R34)/12 -> 102403.75 | AH34: 41743.024 | AI34: =((G34/AH34)-1)*100 -> 101.0815
B35: ( - ) | C35: Desp. Financeiras / Empréstimos | G35: 20000 | H35: 20000 | I35: 20000 | J35: 20000 | K35: 20000 | L35: 20000 | M35: 20000 | N35: 20000 | O35: 20000 | P35: 20000 | Q35: 20000 | R35: 20000 | AF35: =SUM(G35:R35)/12 -> 20000 | AH35: 23021.816 | AI35: =((G35/AH35)-1)*100 -> -13.125879
B36: ( = ) | C36: Total das Saídas | G36: 979687.5 | H36: 1017115 | I36: 1046792.5 | J36: 1103470 | K36: 1136147.5 | L36: 1165825 | M36: 1216502.5 | N36: 1244180 | O36: 1253857.5 | P36: 1315535 | Q36: 1325212.5 | R36: 1334890 | S36: =SUM(S18:S35) -> 198500 | T36: =SUM(T18:T35) -> 0 | U36: =SUM(U18:U35) -> 198500 | V36: =SUM(V18:V35) -> 0 | W36: =SUM(W18:W35) -> 198500 | X36: =SUM(X18:X35) -> 0 | Y36: =SUM(Y18:Y35) -> 210500 | Z36: =SUM(Z18:Z35) -> 0 | ... AF36: =SUM(AF18:AF35) -> 1178267.9 | AH36: 637929.9 | AI36: =((G36/AH36)-1)*100 -> 53.572908
B38: ( = ) | C38: Saldo Final - R$ | G38: =G16-G36 -> 7812.5 | H38: =H16-H36 -> 9885 | I38: =I16-I36 -> 19707.5 | J38: =J16-J36 -> 2530 | K38: =K16-K36 -> 9352.5 | L38: =L16-L36 -> 19175 | M38: =M16-M36 -> 7997.5 | N38: =N16-N36 -> 19820 | ... R38: =R16-R36 -> 87110 | S38: =#REF!-S36 -> #REF! | T38: =#REF!-T36 -> #REF! | U38: =#REF!-U36 -> #REF! | V38: =#REF!-V36 -> #REF! | W38: =#REF!-W36 -> #REF! | X38: =#REF!-X36 -> #REF! | Y38: =#REF!-Y36 -> #REF! | Z38: =#REF!-Z36 -> #REF! | ... AE38: =#REF!-AE36 -> #REF! | AF38: =SUM(G38:R38) -> 317785 | AH38: 98051.917
C39: (Entradas - Saídas) | G39: =IF(OR(G16=0,G36=0),"",G36/G16) -> 0.99208861 | H39: =IF(OR(H16=0,H36=0),"",H36/H16) -> 0.99037488 | I39: =IF(OR(I16=0,I36=0),"",I36/I16) -> 0.98152133 | J39: =IF(OR(J16=0,J36=0),"",J36/J16) -> 0.99771248 | K39: =IF(OR(K16=0,K36=0),"",K36/K16) -> 0.99183544 | L39: =IF(OR(L16=0,L36=0),"",L36/L16) -> 0.98381857 | M39: =IF(OR(M16=0,M36=0),"",M36/M16) -> 0.99346876 | N39: =IF(OR(N16=0,N36=0),"",N36/N16) -> 0.98431962 | ... R39: =IF(OR(R16=0,R36=0),"",R36/R16) -> 0.93874121 | S39: =IF(OR(#REF!=0,S36=0),"",S36/#REF!) -> #REF! | T39: =IF(OR(#REF!=0,T36=0),"",T36/#REF!) -> #REF! | U39: =IF(OR(#REF!=0,U36=0),"",U36/#REF!) -> #REF! | V39: =IF(OR(#REF!=0,V36=0),"",V36/#REF!) -> #REF! | W39: =IF(OR(#REF!=0,W36=0),"",W36/#REF!) -> #REF! | X39: =IF(OR(#REF!=0,X36=0),"",X36/#REF!) -> #REF! | Y39: =IF(OR(#REF!=0,Y36=0),"",Y36/#REF!) -> #REF! | Z39: =IF(OR(#REF!=0,Z36=0),"",Z36/#REF!) -> #REF! | ... AE39: =IF(OR(#REF!=0,AE36=0),"",AE36/#REF!) -> #REF!
